{
  "fields": [
    {
      "metadata": {},
      "name": "_actions",
      "nullable": true,
      "type": {
        "fields": [
          {
            "metadata": {},
            "name": "is_deletable",
            "nullable": true,
            "type": "boolean"
          },
          {
            "metadata": {},
            "name": "is_editable",
            "nullable": true,
            "type": "boolean"
          }
        ],
        "type": "struct"
      }
    },
    {
      "metadata": {},
      "name": "classification",
      "nullable": true,
      "type": {
        "fields": [
          {
            "metadata": {},
            "name": "direction",
            "nullable": true,
            "type": {
              "fields": [
                {
                  "metadata": {},
                  "name": "code",
                  "nullable": true,
                  "type": "string"
                },
                {
                  "metadata": {},
                  "name": "en",
                  "nullable": true,
                  "type": "string"
                },
                {
                  "metadata": {},
                  "name": "et",
                  "nullable": true,
                  "type": "string"
                }
              ],
              "type": "struct"
            }
          },
          {
            "metadata": {},
            "name": "domain",
            "nullable": true,
            "type": {
              "fields": [
                {
                  "metadata": {},
                  "name": "code",
                  "nullable": true,
                  "type": "string"
                },
                {
                  "metadata": {},
                  "name": "en",
                  "nullable": true,
                  "type": "string"
                },
                {
                  "metadata": {},
                  "name": "et",
                  "nullable": true,
                  "type": "string"
                }
              ],
              "type": "struct"
            }
          },
          {
            "metadata": {},
            "name": "group",
            "nullable": true,
            "type": {
              "fields": [
                {
                  "metadata": {},
                  "name": "code",
                  "nullable": true,
                  "type": "string"
                },
                {
                  "metadata": {},
                  "name": "en",
                  "nullable": true,
                  "type": "string"
                },
                {
                  "metadata": {},
                  "name": "et",
                  "nullable": true,
                  "type": "string"
                }
              ],
              "type": "struct"
            }
          },
          {
            "metadata": {},
            "name": "study_group",
            "nullable": true,
            "type": {
              "fields": [
                {
                  "metadata": {},
                  "name": "code",
                  "nullable": true,
                  "type": "string"
                },
                {
                  "metadata": {},
                  "name": "en",
                  "nullable": true,
                  "type": "string"
                },
                {
                  "metadata": {},
                  "name": "et",
                  "nullable": true,
                  "type": "string"
                }
              ],
              "type": "struct"
            }
          },
          {
            "metadata": {},
            "name": "study_level",
            "nullable": true,
            "type": {
              "fields": [
                {
                  "metadata": {},
                  "name": "code",
                  "nullable": true,
                  "type": "string"
                },
                {
                  "metadata": {},
                  "name": "en",
                  "nullable": true,
                  "type": "string"
                },
                {
                  "metadata": {},
                  "name": "et",
                  "nullable": true,
                  "type": "string"
                }
              ],
              "type": "struct"
            }
          },
          {
            "metadata": {},
            "name": "study_type",
            "nullable": true,
            "type": {
              "fields": [
                {
                  "metadata": {},
                  "name": "code",
                  "nullable": true,
                  "type": "string"
                },
                {
                  "metadata": {},
                  "name": "en",
                  "nullable": true,
                  "type": "string"
                },
                {
                  "metadata": {},
                  "name": "et",
                  "nullable": true,
                  "type": "string"
                }
              ],
              "type": "struct"
            }
          }
        ],
        "type": "struct"
      }
    },
    {
      "metadata": {},
      "name": "code",
      "nullable": true,
      "type": "string"
    },
    {
      "metadata": {},
      "name": "curriculum_code",
      "nullable": true,
      "type": "string"
    },
    {
      "metadata": {},
      "name": "general",
      "nullable": true,
      "type": {
        "fields": [
          {
            "metadata": {},
            "name": "input_languages",
            "nullable": true,
            "type": {
              "containsNull": true,
              "elementType": {
                "fields": [
                  {
                    "metadata": {},
                    "name": "code",
                    "nullable": true,
                    "type": "string"
                  },
                  {
                    "metadata": {},
                    "name": "en",
                    "nullable": true,
                    "type": "string"
                  },
                  {
                    "metadata": {},
                    "name": "et",
                    "nullable": true,
                    "type": "string"
                  }
                ],
                "type": "struct"
              },
              "type": "array"
            }
          },
          {
            "metadata": {},
            "name": "year",
            "nullable": true,
            "type": {
              "fields": [
                {
                  "metadata": {},
                  "name": "code",
                  "nullable": true,
                  "type": "string"
                },
                {
                  "metadata": {},
                  "name": "en",
                  "nullable": true,
                  "type": "string"
                },
                {
                  "metadata": {},
                  "name": "et",
                  "nullable": true,
                  "type": "string"
                }
              ],
              "type": "struct"
            }
          }
        ],
        "type": "struct"
      }
    },
    {
      "metadata": {},
      "name": "id",
      "nullable": true,
      "type": "long"
    },
    {
      "metadata": {},
      "name": "last_update",
      "nullable": true,
      "type": "string"
    },
    {
      "metadata": {},
      "name": "modules",
      "nullable": true,
      "type": {
        "fields": [
          {
            "metadata": {},
            "name": "blocks",
            "nullable": true,
            "type": {
              "containsNull": true,
              "elementType": {
                "fields": [
                  {
                    "metadata": {},
                    "name": "max_credits",
                    "nullable": true,
                    "type": "long"
                  },
                  {
                    "metadata": {},
                    "name": "min_credits",
                    "nullable": true,
                    "type": "long"
                  },
                  {
                    "metadata": {},
                    "name": "only_for_others",
                    "nullable": true,
                    "type": "boolean"
                  },
                  {
                    "metadata": {},
                    "name": "order_number",
                    "nullable": true,
                    "type": "long"
                  },
                  {
                    "metadata": {},
                    "name": "target_group_type",
                    "nullable": true,
                    "type": {
                      "fields": [
                        {
                          "metadata": {},
                          "name": "code",
                          "nullable": true,
                          "type": "string"
                        },
                        {
                          "metadata": {},
                          "name": "en",
                          "nullable": true,
                          "type": "string"
                        },
                        {
                          "metadata": {},
                          "name": "et",
                          "nullable": true,
                          "type": "string"
                        }
                      ],
                      "type": "struct"
                    }
                  },
                  {
                    "metadata": {},
                    "name": "title",
                    "nullable": true,
                    "type": {
                      "fields": [
                        {
                          "metadata": {},
                          "name": "en",
                          "nullable": true,
                          "type": "string"
                        },
                        {
                          "metadata": {},
                          "name": "et",
                          "nullable": true,
                          "type": "string"
                        }
                      ],
                      "type": "struct"
                    }
                  },
                  {
                    "metadata": {},
                    "name": "type",
                    "nullable": true,
                    "type": {
                      "fields": [
                        {
                          "metadata": {},
                          "name": "code",
                          "nullable": true,
                          "type": "string"
                        },
                        {
                          "metadata": {},
                          "name": "en",
                          "nullable": true,
                          "type": "string"
                        },
                        {
                          "metadata": {},
                          "name": "et",
                          "nullable": true,
                          "type": "string"
                        }
                      ],
                      "type": "struct"
                    }
                  },
                  {
                    "metadata": {},
                    "name": "uuid",
                    "nullable": true,
                    "type": "string"
                  }
                ],
                "type": "struct"
              },
              "type": "array"
            }
          },
          {
            "metadata": {},
            "name": "is_expanded_major",
            "nullable": true,
            "type": "boolean"
          },
          {
            "metadata": {},
            "name": "max_credits",
            "nullable": true,
            "type": "long"
          },
          {
            "metadata": {},
            "name": "min_credits",
            "nullable": true,
            "type": "long"
          },
          {
            "metadata": {},
            "name": "title",
            "nullable": true,
            "type": {
              "fields": [
                {
                  "metadata": {},
                  "name": "en",
                  "nullable": true,
                  "type": "string"
                },
                {
                  "metadata": {},
                  "name": "et",
                  "nullable": true,
                  "type": "string"
                }
              ],
              "type": "struct"
            }
          },
          {
            "metadata": {},
            "name": "uuid",
            "nullable": true,
            "type": "string"
          }
        ],
        "type": "struct"
      }
    },
    {
      "metadata": {},
      "name": "overview",
      "nullable": true,
      "type": {
        "fields": [
          {
            "metadata": {},
            "name": "description",
            "nullable": true,
            "type": {
              "fields": [
                {
                  "metadata": {},
                  "name": "en",
                  "nullable": true,
                  "type": "string"
                },
                {
                  "metadata": {},
                  "name": "et",
                  "nullable": true,
                  "type": "string"
                }
              ],
              "type": "struct"
            }
          },
          {
            "metadata": {},
            "name": "reception_criteria",
            "nullable": true,
            "type": {
              "fields": [
                {
                  "metadata": {},
                  "name": "en",
                  "nullable": true,
                  "type": "string"
                },
                {
                  "metadata": {},
                  "name": "et",
                  "nullable": true,
                  "type": "string"
                }
              ],
              "type": "struct"
            }
          }
        ],
        "type": "struct"
      }
    },
    {
      "metadata": {},
      "name": "state",
      "nullable": true,
      "type": {
        "fields": [
          {
            "metadata": {},
            "name": "code",
            "nullable": true,
            "type": "string"
          },
          {
            "metadata": {},
            "name": "en",
            "nullable": true,
            "type": "string"
          },
          {
            "metadata": {},
            "name": "et",
            "nullable": true,
            "type": "string"
          }
        ],
        "type": "struct"
      }
    },
    {
      "metadata": {},
      "name": "uuid",
      "nullable": true,
      "type": "string"
    }
  ],
  "type": "struct"
}